nms/__init__.py
nms/fast.py
nms/felzenszwalb.py
nms/helpers.py
nms/malisiewicz.py
nms/nms.py
nms-0.1.6.dist-info/METADATA
nms-0.1.6.dist-info/RECORD
nms-0.1.6.dist-info/WHEEL
nms-0.1.6.dist-info/top_level.txt
