Metadata-Version: 2.1
Name: nms
Version: 0.1.6
Summary: A Non Maximal Suppression Python Package
Home-page: https://bitbucket.com/tomhoag/nms
Author: Tom Hoag
Author-email: tomhoag@gmail.com
License: UNKNOWN
Keywords: non maximal suppression,non maximum suppression,opencv,image processing
Platform: UNKNOWN
Classifier: Programming Language :: Python :: 3
Classifier: License :: OSI Approved :: MIT License
Classifier: Operating System :: OS Independent
